paperize/__init__.py
paperize/main.py
paperize-1.0.2.dist-info/DESCRIPTION.rst
paperize-1.0.2.dist-info/METADATA
paperize-1.0.2.dist-info/RECORD
paperize-1.0.2.dist-info/WHEEL
paperize-1.0.2.dist-info/entry_points.txt
paperize-1.0.2.dist-info/metadata.json
paperize-1.0.2.dist-info/top_level.txt
