Metadata-Version: 2.0
Name: paperize
Version: 1.0.2
Summary: Converts a binary file to printable QR codes and back
Home-page: https://github.com/faerbit/paperize
Author: Faerbit
Author-email: faerbit at gmail dot com
License: MIT
Platform: UNKNOWN
Classifier: Development Status :: 4 - Beta
Classifier: License :: OSI Approved :: MIT License
Classifier: Environment :: Console
Classifier: Intended Audience :: Developers
Classifier: Intended Audience :: System Administrators
Classifier: Programming Language :: Python :: 3
Classifier: Programming Language :: Python :: 3.6
Classifier: Programming Language :: Python :: 3 :: Only
Classifier: Operating System :: OS Independent
Requires-Dist: pypandoc
Requires-Dist: qrcode
